LICENSE
gwdc_python/__init__.py
gwdc_python/constants.py
gwdc_python/exceptions.py
gwdc_python/files/__init__.py
gwdc_python/files/constants.py
gwdc_python/files/file_reference.py
gwdc_python/files/filters.py
gwdc_python/files/identifiers.py
gwdc_python/files/tests/__init__.py
gwdc_python/files/tests/test_file_reference.py
gwdc_python/files/tests/test_filters.py
gwdc_python/files/tests/test_identifiers.py
gwdc_python/gwdc.py
gwdc_python/helpers.py
gwdc_python/logger.py
gwdc_python/objects/__init__.py
gwdc_python/objects/base.py
gwdc_python/objects/meta.py
gwdc_python/objects/tests/__init__.py
gwdc_python/objects/tests/test_base.py
gwdc_python/objects/tests/test_meta.py
gwdc_python/settings.py
gwdc_python/tests/__init__.py
gwdc_python/tests/test_gwdc_python.py
gwdc_python/utils/__init__.py
gwdc_python/utils/tests/__init__.py
gwdc_python/utils/tests/test_utils.py
gwdc_python/utils/typed_list.py
gwdc_python/utils/utils.py
gwdc_python-1.0.0.dist-info/LICENSE
gwdc_python-1.0.0.dist-info/METADATA
gwdc_python-1.0.0.dist-info/WHEEL
gwdc_python-1.0.0.dist-info/RECORD
